odoo/addons/base_binary_url_import/README.rst
odoo/addons/base_binary_url_import/__init__.py
odoo/addons/base_binary_url_import/__manifest__.py
odoo/addons/base_binary_url_import/data/ir_config_parameter.xml
odoo/addons/base_binary_url_import/i18n/base_binary_url_import.pot
odoo/addons/base_binary_url_import/i18n/es.po
odoo/addons/base_binary_url_import/i18n/it.po
odoo/addons/base_binary_url_import/readme/CONFIGURE.rst
odoo/addons/base_binary_url_import/readme/CONTRIBUTORS.rst
odoo/addons/base_binary_url_import/readme/CREDITS.rst
odoo/addons/base_binary_url_import/readme/DESCRIPTION.rst
odoo/addons/base_binary_url_import/readme/ROADMAP.rst
odoo/addons/base_binary_url_import/readme/USAGE.rst
odoo/addons/base_binary_url_import/security/ir.model.access.csv
odoo/addons/base_binary_url_import/static/description/icon.png
odoo/addons/base_binary_url_import/static/description/index.html
odoo/addons/base_binary_url_import/wizard/__init__.py
odoo/addons/base_binary_url_import/wizard/base_binary_url_import.py
odoo/addons/base_binary_url_import/wizard/base_binary_url_import_view.xml
odoo_addon_base_binary_url_import-16.0.1.0.0.9.dist-info/METADATA
odoo_addon_base_binary_url_import-16.0.1.0.0.9.dist-info/WHEEL
odoo_addon_base_binary_url_import-16.0.1.0.0.9.dist-info/top_level.txt
odoo_addon_base_binary_url_import-16.0.1.0.0.9.dist-info/RECORD
